lassare/__init__.py
lassare-0.0.1.dist-info/METADATA
lassare-0.0.1.dist-info/WHEEL
lassare-0.0.1.dist-info/RECORD
