Metadata-Version: 2.4
Name: lassare
Version: 0.0.1
Summary: Human-in-the-loop API for AI agents. Coming soon.
Project-URL: Homepage, https://lassare.com
Project-URL: Repository, https://github.com/lassare-hq/lassare-python
Author: Lassare
License-Expression: MIT
Keywords: agents,ai,approval,hitl,human-in-the-loop,mcp
Classifier: Development Status :: 1 - Planning
Classifier: Intended Audience :: Developers
Classifier: License :: OSI Approved :: MIT License
Classifier: Programming Language :: Python :: 3
Classifier: Programming Language :: Python :: 3.8
Classifier: Programming Language :: Python :: 3.9
Classifier: Programming Language :: Python :: 3.10
Classifier: Programming Language :: Python :: 3.11
Classifier: Programming Language :: Python :: 3.12
Requires-Python: >=3.8
